hyperglyph/__init__.py
hyperglyph/data.py
hyperglyph/encoding.py
hyperglyph/server.py
hyperglyph/resource/__init__.py
hyperglyph/resource/base.py
hyperglyph/resource/handler.py
hyperglyph/resource/persistent.py
hyperglyph/resource/router.py
hyperglyph/resource/transient.py
hyperglyph-0.9_20140421.dist-info/DESCRIPTION.rst
hyperglyph-0.9_20140421.dist-info/METADATA
hyperglyph-0.9_20140421.dist-info/metadata.json
hyperglyph-0.9_20140421.dist-info/RECORD
hyperglyph-0.9_20140421.dist-info/top_level.txt
hyperglyph-0.9_20140421.dist-info/WHEEL
