Metadata-Version: 2.0
Name: hyperglyph
Version: 0.9-20140421
Summary: hyperglyph is ducked typed ipc over http
Home-page: UNKNOWN
Author: tef
Author-email: tef@twentygototen.org
License: MIT License
Platform: UNKNOWN
Requires-Dist: werkzeug
Requires-Dist: requests
Requires-Dist: pytz
Requires-Dist: isodate
